MANIFEST.in
README.rst
setup.cfg
setup.py
klempner/__init__.py
klempner/compat.py
klempner/config.py
klempner/errors.py
klempner/url.py
klempner.egg-info/PKG-INFO
klempner.egg-info/SOURCES.txt
klempner.egg-info/dependency_links.txt
klempner.egg-info/requires.txt
klempner.egg-info/top_level.txt
tests/__init__.py
tests/helpers.py
tests/test_config.py
tests/test_consul_discovery.py
tests/test_env_discovery.py
tests/test_k8s_discovery.py
tests/test_url_building.py