Metadata-Version: 2.1
Name: klempner
Version: 0.0.2
Summary: Construct service request URLs
Home-page: https://github.com/dave-shawley/klempner
Author: Dave Shawley
Author-email: daveshawley@gmail.com
License: UNKNOWN
Platform: UNKNOWN
Classifier: Development Status :: 3 - Alpha
Classifier: Environment :: Web Environment
Classifier: Intended Audience :: Developers
Classifier: License :: OSI Approved :: BSD License
Classifier: Programming Language :: Python :: 2.7
Classifier: Programming Language :: Python :: 3.5
Classifier: Programming Language :: Python :: 3.6
Classifier: Programming Language :: Python :: 3.7
Classifier: Topic :: Software Development :: Libraries
Provides-Extra: docs
Provides-Extra: dev
